ordeq_toml/__init__.py
ordeq_toml/_version.py
ordeq_toml/py.typed
ordeq_toml/toml.py
ordeq_toml-1.0.0.dist-info/licenses/LICENSE
ordeq_toml-1.0.0.dist-info/METADATA
ordeq_toml-1.0.0.dist-info/WHEEL
ordeq_toml-1.0.0.dist-info/top_level.txt
ordeq_toml-1.0.0.dist-info/RECORD
