Metadata-Version: 2.4
Name: ordeq_toml
Version: 1.0.0
Author: Niels Neerhoff, Simon Brugman
Maintainer: Niels Neerhoff, Simon Brugman
License-Expression: MIT
Requires-Python: >=3.10
License-File: LICENSE
Requires-Dist: ordeq>=1.0.0
Requires-Dist: tomli>=1.1.0; python_version < "3.11"
Requires-Dist: tomli-w
Dynamic: license-file
